data_stream_kit/__init__.py
data_stream_kit/lock.py
data_stream_kit/pipeline.py
data_stream_kit/kafka_asyncio/__init__.py
data_stream_kit/kafka_asyncio/hander.py
data_stream_kit/kafka_libs/__init__.py
data_stream_kit/kafka_libs/handler.py
data_stream_kit/kafka_libs/mapping.py
data_stream_kit/kafka_libs/util.py
data_stream_kit/sqla_asyncio/__init__.py
data_stream_kit/sqla_asyncio/curd.py
data_stream_kit/sqla_asyncio/manager.py
data_stream_kit/sqla_decorator/__init__.py
data_stream_kit/sqla_decorator/engine.py
data_stream_kit/sqla_decorator/manager.py
data_stream_kit/sqla_decorator/models.py
data_stream_kit/sqla_decorator/session_ctx.py
data_stream_kit/sqla_decorator/utils/__init__.py
data_stream_kit/sqla_decorator/utils/db.py
data_stream_kit/sqla_decorator/utils/explain.py
data_stream_kit/sqla_decorator/utils/query_count.py
data_stream_kit/sqla_decorator/utils/tool.py
data_stream_kit-0.0.3.dist-info/METADATA
data_stream_kit-0.0.3.dist-info/WHEEL
data_stream_kit-0.0.3.dist-info/top_level.txt
data_stream_kit-0.0.3.dist-info/RECORD
