Metadata-Version: 2.1
Name: data-stream-kit
Version: 0.0.3
Summary: 数据处理工具
Author: huangkewei
Requires-Dist: sqlalchemy[asyncio] ~=1.4.0
Requires-Dist: pottery ~=3.0.0
Requires-Dist: regex ~=2022.7.0
Requires-Dist: cchardet ~=2.1.0
Requires-Dist: werkzeug ~=2.3.0
Requires-Dist: pymysql ~=1.0.0
Requires-Dist: aiomysql ~=0.1.0
Requires-Dist: confluent-kafka
Requires-Dist: psutil ~=5.8.0
